{"initial_url":"https://www.neoncrm.com/solutions-animal-wildlife/","final_url":"https://www.neoncrm.com/solutions-animal-wildlife/","canonical_url":"https://www.neoncrm.com/solutions-animal-wildlife/","title":"Animal and Wildlife Organizations | Neon Nonprofit Software Solutions","http_status":200,"links":["https://www.neoncrm.com/neoncrm-features/","https://www.neoncrm.com/neoncrm-features/","https://www.neoncrm.com/nonprofit-software-2/","https://www.neoncrm.com/fundraising-software/","https://www.neoncrm.com/membership-software/","https://www.neoncrm.com/event-management-software/","https://www.neoncrm.com/nonprofit-marketing-communications-software/","https://www.neoncrm.com/dashboards/","https://www.neoncrm.com/workflows/","https://www.neoncrm.com/custom-objects/","https://www.neoncrm.com/neon-one/","https://www.neoncrm.com/missions/","https://www.neoncrm.com/solutions-arts-culture-orgs/","https://www.neoncrm.com/solutions-animal-wildlife/","https://www.neoncrm.com/solutions-youth-organizations/","https://www.neoncrm.com/solutions-human-services-organizations/","https://www.neoncrm.com/solutions-social-justice-activism-organizations/","https://www.neoncrm.com/solutions-foundations/","https://www.neoncrm.com/solutions-education/","https://www.neoncrm.com/solutions-faith-organizations/","https://www.neoncrm.com/solutions-medical-wellness-organizations/","https://www.neoncrm.com/solutions-environmental-organizations/","https://www.neoncrm.com/solutions-professional-associations-membership/","https://www.neoncrm.com/solutions-international-humanitarian-orgs/","https://www.neoncrm.com/pro-services/","https://www.neoncrm.com/pro-services/","https://www.neoncrm.com/neon-one-dev/","https://www.neoncrm.com/payment-processing/","https://www.neoncrm.com/nonprofit-websites/","https://www.neoncrm.com/pricing/","https://www2.neoncrm.com/nc-personal-demo","https://www.neoncrm.com/","https://www.neoncrm.com/neoncrm-features/","https://www.neoncrm.com/neoncrm-features/","https://www.neoncrm.com/nonprofit-software-2/","https://www.neoncrm.com/fundraising-software/","https://www.neoncrm.com/membership-software/","https://www.neoncrm.com/event-management-software/","https://www.neoncrm.com/nonprofit-marketing-communications-software/","https://www.neoncrm.com/dashboards/","https://www.neoncrm.com/workflows/","https://www.neoncrm.com/custom-objects/","https://www.neoncrm.com/neon-one/","https://www.neoncrm.com/missions/","https://www.neoncrm.com/solutions-arts-culture-orgs/","https://www.neoncrm.com/solutions-animal-wildlife/","https://www.neoncrm.com/solutions-youth-organizations/","https://www.neoncrm.com/solutions-human-services-organizations/","https://www.neoncrm.com/solutions-social-justice-activism-organizations/","https://www.neoncrm.com/solutions-foundations/","https://www.neoncrm.com/solutions-education/","https://www.neoncrm.com/solutions-faith-organizations/","https://www.neoncrm.com/solutions-medical-wellness-organizations/","https://www.neoncrm.com/solutions-environmental-organizations/","https://www.neoncrm.com/solutions-professional-associations-membership/","https://www.neoncrm.com/solutions-international-humanitarian-orgs/","https://www.neoncrm.com/pro-services/","https://www.neoncrm.com/pro-services/","https://www.neoncrm.com/neon-one-dev/","https://www.neoncrm.com/payment-processing/","https://www.neoncrm.com/nonprofit-websites/","https://www.neoncrm.com/pricing/","https://www2.neoncrm.com/nc-personal-demo","https://www2.neoncrm.com/nc-personal-demo","https://www.neoncrm.com/nonprofit-marketing-communications-software/","https://www.neoncrm.com/donor-management-software/","https://www.neoncrm.com/membership-software/","https://www.neoncrm.com/reports-analytics/","https://www.neoncrm.com/online-forms/","https://www.neoncrm.com/nonprofit-software/","https://www.neoncrm.com/event-management-software/","https://www.neoncrm.com/nonprofit-marketing-communications-software/","https://www.neoncrm.com/nonprofit-websites/","https://www.neoncrm.com/nonprofit-marketing-communications-software/","https://www.neoncrm.com/reports-analytics/","https://www.neoncrm.com/fund-campaign-tracking/","https://www.neoncrm.com/nonprofit-marketing-communications-software/","https://www.neoncrm.com/donation-receipt/","https://www.neoncrm.com/online-forms/","https://www.neoncrm.com/nonprofit-know-lawrence-humane-society/","https://www.neoncrm.com/demo/","https://www.neoncrm.com/nonprofit-know-lawrence-humane-society/","https://www.neoncrm.com/demo/"],"time":1596062538920,"path":"/solutions-animal-wildlife/","host":"neoncrm.com","lighthouse":{"mobile":{"page_speed":0.03,"a11y":0.82,"seo":0.97,"best_practices":0.79},"desktop":{"page_speed":0.08,"a11y":0.86,"seo":1,"best_practices":0.79}},"screen_shots":{"mobile":"lh","desktop":"lh"}}